dynamodb_meta_store/__init__.py
dynamodb_meta_store/exceptions.py
dynamodb_meta_store/meta_store.py
dynamodb_meta_store-0.4.1.dist-info/LICENSE
dynamodb_meta_store-0.4.1.dist-info/METADATA
dynamodb_meta_store-0.4.1.dist-info/WHEEL
dynamodb_meta_store-0.4.1.dist-info/top_level.txt
dynamodb_meta_store-0.4.1.dist-info/RECORD
