Metadata-Version: 2.1
Name: dynamodb-meta-store
Version: 0.4.1
Summary: Store metadata using DynamoDB as backend
Home-page: https://github.com/sergeymazin/dynamodb-meta-store
Author: Sergey Mazin
Author-email: sergey.mazin@hotmail.com
License: UNKNOWN
Download-URL: https://github.com/sergeymazin/dynamodb-meta-store/tarball/master
Keywords: dynamodb,aws,config,metadata
Platform: Any
Classifier: Development Status :: 3 - Alpha
Classifier: License :: OSI Approved :: Apache Software License
Classifier: Programming Language :: Python
Classifier: Programming Language :: Python :: 3 :: Only
Classifier: Programming Language :: Python :: 3.6
Classifier: Intended Audience :: Developers
Classifier: Environment :: Console
Requires-Dist: boto3
Provides-Extra: dev
Requires-Dist: pre-commit ; extra == 'dev'
Requires-Dist: flake8 ; extra == 'dev'
Requires-Dist: flake8-quotes ; extra == 'dev'
Requires-Dist: twine ; extra == 'dev'
